pyneutralino/__init__.py
pyneutralino/neutralino-linux
pyneutralino/neutralino-mac
pyneutralino/neutralino-win.exe
pyneutralino/neutralino.py
pyneutralino/app/index.html
pyneutralino/app/settings.json
pyneutralino-1.0.2.dist-info/LICENSE
pyneutralino-1.0.2.dist-info/METADATA
pyneutralino-1.0.2.dist-info/WHEEL
pyneutralino-1.0.2.dist-info/top_level.txt
pyneutralino-1.0.2.dist-info/RECORD
